[
  {
    "ContainingType": "EmployeePortal_Angular_CoreWebApi.Controllers.EmployeeController",
    "Method": "GetEmployees",
    "RelativePath": "api/Employee",
    "HttpMethod": "GET",
    "IsController": true,
    "Order": 0,
    "Parameters": [],
    "ReturnTypes": []
  },
  {
    "ContainingType": "EmployeePortal_Angular_CoreWebApi.Controllers.EmployeeController",
    "Method": "AddEmployee",
    "RelativePath": "api/Employee",
    "HttpMethod": "POST",
    "IsController": true,
    "Order": 0,
    "Parameters": [
      {
        "Name": "employee",
        "Type": "EmployeePortal_Angular_CoreWebApi.Models.Employee",
        "IsRequired": true
      }
    ],
    "ReturnTypes": []
  },
  {
    "ContainingType": "EmployeePortal_Angular_CoreWebApi.Controllers.EmployeeController",
    "Method": "UpdateEmployee",
    "RelativePath": "api/Employee/{id}",
    "HttpMethod": "PUT",
    "IsController": true,
    "Order": 0,
    "Parameters": [
      {
        "Name": "id",
        "Type": "System.Int32",
        "IsRequired": true
      },
      {
        "Name": "employee",
        "Type": "EmployeePortal_Angular_CoreWebApi.Models.Employee",
        "IsRequired": true
      }
    ],
    "ReturnTypes": []
  },
  {
    "ContainingType": "EmployeePortal_Angular_CoreWebApi.Controllers.EmployeeController",
    "Method": "DeleteEmployee",
    "RelativePath": "api/Employee/{id}",
    "HttpMethod": "DELETE",
    "IsController": true,
    "Order": 0,
    "Parameters": [
      {
        "Name": "id",
        "Type": "System.Int32",
        "IsRequired": true
      }
    ],
    "ReturnTypes": []
  },
  {
    "ContainingType": "EmployeePortal_Angular_CoreWebApi.Controllers.EmployeeController",
    "Method": "PatchEmployee",
    "RelativePath": "api/Employee/{id}",
    "HttpMethod": "PATCH",
    "IsController": true,
    "Order": 0,
    "Parameters": [
      {
        "Name": "id",
        "Type": "System.Int32",
        "IsRequired": true
      },
      {
        "Name": "employeePatchDoc",
        "Type": "Microsoft.AspNetCore.JsonPatch.Operations.Operation[]",
        "IsRequired": true
      }
    ],
    "ReturnTypes": []
  }
]